[
  {
    "id": "00010203-0405-0607-0809-0a0b0c0d0e0f",
    "nome": "Caio",
    "email": "aluno@gmail.com",
    "senha": "321",
    "tipo": "aluno",
    "materias": [
      "Portugu\u00eas",
      "Matem\u00e1tica",
      "Hist\u00f3ria",
      "Geografia",
      "F\u00edsica",
      "Qu\u00edmica",
      "Ingl\u00eas"
    ],
    "duvidas": [
      {
        "id_duvida": "",
        "pergunta": "",
        "reposta": "",
        "materia": ""
      }
    ]
  },
  {
    "id": "c9c58a02-4d6b-11ed-a554-00155d091aa6",
    "nome": "Thiago Santos",
    "email": "thiagomtd2@gmail.com",
    "senha": "12345678",
    "tipo": "aluno",
    "materias": [
      "Hist\u00f3ria",
      "Portugu\u00eas"
    ],
    "duvidas": []
  }
]